ADT/Class instance of Type.ipynb
ADT/PySimpleGUI.py
ADT/README.md
ADT/__init__.py
ADT/basictypes.py
ADT/calendar.png
ADT/collayout.py
ADT/dnd_example1.py
ADT/dnd_example2.py
ADT/fonctors.py
ADT/hbds.py
ADT/images.py
ADT/ipyadt.py
ADT/jsonify.py
ADT/output.py
ADT/querytree.py
ADT/querytree2.py
ADT/querytree3.py
ADT/sgadt.py
ADT/sgadt2.py
ADT/units.py
ADT/util.py
ADTthious-0.5.dist-info/LICENSE
ADTthious-0.5.dist-info/METADATA
ADTthious-0.5.dist-info/WHEEL
ADTthious-0.5.dist-info/top_level.txt
ADTthious-0.5.dist-info/RECORD
