Metadata-Version: 2.1
Name: ADTthious
Version: 0.5
Summary: Abstract Data Types for python
Home-page: https://github.com/gitthious/ADT.git
Author: Thierry Hervé
Author-email: thious.rv@gmail.com
License: UNKNOWN
Platform: UNKNOWN
Classifier: Programming Language :: Python :: 3 :: Only
Classifier: Development Status :: 3 - Alpha
Classifier: License :: OSI Approved :: MIT License
Classifier: Operating System :: OS Independent
Classifier: Topic :: Software Development :: Libraries :: Python Modules
Requires-Dist: colour (==0.1.5)
Requires-Dist: PySimpleGUI (==4.0.0)
Requires-Dist: pipe (==1.6.0)
Requires-Dist: python-dateutil (==2.8.1)
